go/__init__.py
go/deploy.py
go/ssh_helper.py
go/utils.py
go_deploy-0.4.3.dist-info/LICENSE
go_deploy-0.4.3.dist-info/METADATA
go_deploy-0.4.3.dist-info/WHEEL
go_deploy-0.4.3.dist-info/entry_points.txt
go_deploy-0.4.3.dist-info/top_level.txt
go_deploy-0.4.3.dist-info/RECORD
