Metadata-Version: 2.1
Name: go-deploy
Version: 0.4.3
Summary: Provision using terraform and ansible
Home-page: https://github.com/geneontology/devops-deployment-scripts.git
Author: Abdelilah Essiari
Author-email: aessiari@lbl.gov
Classifier: Programming Language :: Python :: 3
Classifier: License :: OSI Approved :: BSD License
Classifier: Operating System :: OS Independent
Requires-Python: >=3.8
License-File: LICENSE
Requires-Dist: pyyaml >=6.0
Requires-Dist: paramiko >=2.11.0
